smfret_bondtime/__init__.py
smfret_bondtime/__main__.py
smfret_bondtime/_version.py
smfret_bondtime/analysis.py
smfret_bondtime/io.py
smfret_bondtime/sciform_lite.py
smfret_bondtime/gui/BleedThrough.qml
smfret_bondtime/gui/Changepoints.qml
smfret_bondtime/gui/Filter.qml
smfret_bondtime/gui/Locator.qml
smfret_bondtime/gui/Results.qml
smfret_bondtime/gui/TrackNavigator.qml
smfret_bondtime/gui/Tracker.qml
smfret_bondtime/gui/__init__.py
smfret_bondtime/gui/backend.py
smfret_bondtime/gui/changepoints.py
smfret_bondtime/gui/filter.py
smfret_bondtime/gui/image_pipeline.py
smfret_bondtime/gui/main.qml
smfret_bondtime/gui/results.py
smfret_bondtime/gui/track_navigator.py
smfret_bondtime-2.0.0.dist-info/METADATA
smfret_bondtime-2.0.0.dist-info/WHEEL
smfret_bondtime-2.0.0.dist-info/entry_points.txt
smfret_bondtime-2.0.0.dist-info/licenses/LICENSES/BSD-3-Clause.txt
smfret_bondtime-2.0.0.dist-info/licenses/LICENSES/CC-BY-SA-4.0.txt
smfret_bondtime-2.0.0.dist-info/licenses/LICENSES/CC0-1.0.txt
smfret_bondtime-2.0.0.dist-info/licenses/LICENSES/MIT.txt
smfret_bondtime-2.0.0.dist-info/RECORD
