Metadata-Version: 2.4
Name: smfret-bondtime
Version: 2.0.0
Summary: Infer receptor–ligand bond lifetimes from smFRET data
Project-URL: repository, https://github.com/schuetzgroup/smfret-bondtime
Author-email: Lukas Schrangl <lukas.schrangl@boku.ac.at>
Maintainer-email: Lukas Schrangl <lukas.schrangl@boku.ac.at>
License-Expression: BSD-3-Clause AND MIT AND CC-BY-SA-4.0
License-File: LICENSES/BSD-3-Clause.txt
License-File: LICENSES/CC-BY-SA-4.0.txt
License-File: LICENSES/CC0-1.0.txt
License-File: LICENSES/MIT.txt
Classifier: Development Status :: 5 - Production/Stable
Classifier: Intended Audience :: Science/Research
Classifier: Operating System :: OS Independent
Classifier: Programming Language :: Python :: 3
Classifier: Programming Language :: Python :: 3 :: Only
Classifier: Topic :: Scientific/Engineering
Classifier: Topic :: Scientific/Engineering :: Bio-Informatics
Classifier: Topic :: Scientific/Engineering :: Image Processing
Classifier: Topic :: Scientific/Engineering :: Information Analysis
Classifier: Topic :: Scientific/Engineering :: Physics
Requires-Python: >=3.10
Requires-Dist: lifelines
Requires-Dist: matplotlib
Requires-Dist: numpy
Requires-Dist: pandas
Requires-Dist: pyqt5
Requires-Dist: scipy
Requires-Dist: sdt-python>=19.0.1
Requires-Dist: trackpy
